NOTICE
gen3users/__init__.py
gen3users/base_abac.json
gen3users/conversion.py
gen3users/main.py
gen3users/user_security.py
gen3users/validation.py
gen3users-1.1.1.dist-info/LICENSE
gen3users-1.1.1.dist-info/METADATA
gen3users-1.1.1.dist-info/NOTICE
gen3users-1.1.1.dist-info/WHEEL
gen3users-1.1.1.dist-info/entry_points.txt
gen3users-1.1.1.dist-info/RECORD
