Metadata-Version: 2.1
Name: gen3users
Version: 1.1.1
Summary: Utils for Gen3 Commons user management
Home-page: https://github.com/uc-cdis/gen3users
License: Apache-2.0
Author: CTDS UChicago
Author-email: cdis@uchicago.edu
Requires-Python: >=3.9,<4.0
Classifier: License :: OSI Approved :: Apache Software License
Classifier: Programming Language :: Python :: 3
Classifier: Programming Language :: Python :: 3.9
Classifier: Programming Language :: Python :: 3.10
Classifier: Programming Language :: Python :: 3.11
Classifier: Programming Language :: Python :: 3.12
Requires-Dist: cdislogging (>=1,<2)
Requires-Dist: click
Requires-Dist: pyyaml (>=6,<7)
Requires-Dist: requests
Project-URL: Repository, https://github.com/uc-cdis/gen3users
